README.txt
setup.cfg
setup.py
docs/HISTORY.txt
docs/INSTALL.txt
docs/LICENSE.GPL
docs/LICENSE.txt
easyshop/__init__.py
easyshop.payment.egg-info/PKG-INFO
easyshop.payment.egg-info/SOURCES.txt
easyshop.payment.egg-info/dependency_links.txt
easyshop.payment.egg-info/entry_points.txt
easyshop.payment.egg-info/namespace_packages.txt
easyshop.payment.egg-info/not-zip-safe
easyshop.payment.egg-info/requires.txt
easyshop.payment.egg-info/top_level.txt
easyshop/payment/__init__.py
easyshop/payment/config.py
easyshop/payment/configure.zcml
easyshop/payment/profiles.zcml
easyshop/payment/tests.py
easyshop/payment/adapters/__init__.py
easyshop/payment/adapters/completeness.py
easyshop/payment/adapters/configure.zcml
easyshop/payment/adapters/payment_information_management.py
easyshop/payment/adapters/payment_method_management.py
easyshop/payment/adapters/payment_price_management.py
easyshop/payment/adapters/payment_processing.py
easyshop/payment/adapters/type.py
easyshop/payment/browser/__init__.py
easyshop/payment/browser/bank_account.py
easyshop/payment/browser/configure.zcml
easyshop/payment/browser/credit_card.py
easyshop/payment/browser/payment_method.pt
easyshop/payment/browser/payment_method.py
easyshop/payment/browser/payment_methods.pt
easyshop/payment/browser/payment_methods.py
easyshop/payment/browser/payment_price.pt
easyshop/payment/browser/payment_price.py
easyshop/payment/browser/payment_prices.pt
easyshop/payment/browser/payment_prices.py
easyshop/payment/browser/paypal.py
easyshop/payment/content/__init__.py
easyshop/payment/content/bank_account.py
easyshop/payment/content/configure.zcml
easyshop/payment/content/containers.py
easyshop/payment/content/credit_card.py
easyshop/payment/content/direct_debit.py
easyshop/payment/content/generic_payment_method.py
easyshop/payment/content/payment_price.py
easyshop/payment/content/payment_result.py
easyshop/payment/content/paypal.py
easyshop/payment/profiles/default/factorytool.xml
easyshop/payment/profiles/default/types.xml
easyshop/payment/profiles/default/workflows.xml
easyshop/payment/profiles/default/types/BankAccount.xml
easyshop/payment/profiles/default/types/CreditCard.xml
easyshop/payment/profiles/default/types/CreditCardPaymentMethod.xml
easyshop/payment/profiles/default/types/DirectDebitPaymentMethod.xml
